users/__init__.py
users/admin.py
users/apps.py
users/models.py
users/tests.py
users/views.py
users/migrations/0001_initial.py
users/migrations/0002_user_mbank_number.py
users/migrations/__init__.py
utils/__init__.py
utils/fields.py
utils/models.py
utils/serializers.py
utils/utils.py
rest_framework_auth_verify-0.0.1.dist-info/METADATA
rest_framework_auth_verify-0.0.1.dist-info/WHEEL
rest_framework_auth_verify-0.0.1.dist-info/top_level.txt
rest_framework_auth_verify-0.0.1.dist-info/RECORD
