Metadata-Version: 2.1
Name: rest-framework-auth-verify
Version: 0.0.1
Summary: This is the simplest module for quick work with files.
Author: baxtdev
Author-email: habibulaevhushbaht05@gmail.com
License: MIT License
Keywords: files speedfiles
Classifier: Programming Language :: Python :: 3.11
Classifier: License :: OSI Approved :: MIT License
Classifier: Operating System :: OS Independent
Requires-Python: >=3.6
Requires-Dist: django
Requires-Dist: djangorestframework
